{
  "website": "https://www.sendgrid.com",
  "domain": "www.sendgrid.com",
  "scraped_at": "2025-11-08 13:58:43",
  "menus": [
    {
      "menu_name": "Products",
      "sections": [
        {
          "section_title": "Email API",
          "items": [
            {
              "title": "Overview a right arrow",
              "description": "",
              "url": "https://sendgrid.com/en-us/solutions/email-api"
            },
            {
              "title": "Take a tour a right arrow",
              "description": "",
              "url": "https://sendgrid.com/en-us/email-api-tour"
            }
          ]
        }
      ]
    },
    {
      "menu_name": "Why SendGrid",
      "sections": [
        {
          "section_title": "Overview",
          "items": [
            {
              "title": "Why Twilio SendGrid a right arrow",
              "description": "",
              "url": "https://sendgrid.com/en-us/why-sendgrid"
            },
            {
              "title": "Calculate Your Email ROI",
              "description": "",
              "url": "https://www.sendgrid.com/en-us/resource/roi-calculator"
            },
            {
              "title": "Our Delivery Rates",
              "description": "",
              "url": "https://www.sendgrid.com/en-us/email-delivery"
            },
            {
              "title": "Free Plan",
              "description": "",
              "url": "https://www.sendgrid.com/en-us/free"
            },
            {
              "title": "Email + SMS, WhatsApp, and More",
              "description": "",
              "url": "https://www.sendgrid.com/en-us/solutions/multichannel"
            }
          ]
        },
        {
          "section_title": "Solutions",
          "items": [
            {
              "title": "Email Solutions a right arrow",
              "description": "",
              "url": "https://sendgrid.com/en-us/solutions"
            }
          ]
        }
      ]
    },
    {
      "menu_name": "Resources",
      "sections": [
        {
          "section_title": "Resources",
          "items": [
            {
              "title": "Guides",
              "description": "",
              "url": "https://www.twilio.com/en-us/resource-center/guides?page=1&solution=email"
            },
            {
              "title": "Blog",
              "description": "",
              "url": "https://www.twilio.com/en-us/blog"
            }
          ]
        }
      ]
    },
    {
      "menu_name": "Developers",
      "sections": [
        {
          "section_title": null,
          "items": [
            {
              "title": "View docs a right arrow",
              "description": "",
              "url": "https://docs.sendgrid.com/for-developers"
            },
            {
              "title": "Start in 5 Minutes",
              "description": "",
              "url": "https://docs.sendgrid.com/for-developers/sending-email/api-getting-started"
            },
            {
              "title": "API Reference",
              "description": "",
              "url": "https://docs.sendgrid.com/api-reference/how-to-use-the-sendgrid-v3-api/authentication"
            },
            {
              "title": "Event Webhook",
              "description": "",
              "url": "https://docs.sendgrid.com/for-developers/tracking-events/event"
            },
            {
              "title": "Libraries",
              "description": "",
              "url": "https://github.com/sendgrid/"
            }
          ]
        }
      ]
    },
    {
      "menu_name": "Contact us",
      "sections": [
        {
          "section_title": "Support",
          "items": [
            {
              "title": "Contact support a right arrow",
              "description": "",
              "url": "https://support.sendgrid.com/"
            }
          ]
        }
      ]
    },
    {
      "menu_name": "Navigation",
      "sections": [
        {
          "section_title": null,
          "items": [
            {
              "title": "Pricing",
              "description": "",
              "url": "https://www.sendgrid.com/en-us/pricing"
            },
            {
              "title": "Start for free",
              "description": "",
              "url": "https://signup.sendgrid.com/"
            },
            {
              "title": "SMTP Service",
              "description": "",
              "url": "https://www.sendgrid.com/en-us/solutions/email-api/smtp-service"
            },
            {
              "title": "Email Validation",
              "description": "",
              "url": "https://www.sendgrid.com/en-us/solutions/email-api/email-address-validation-api"
            },
            {
              "title": "Deliverability Insights",
              "description": "",
              "url": "https://www.sendgrid.com/en-us/solutions/email-api/deliverability-insights"
            },
            {
              "title": "Dynamic Templates",
              "description": "",
              "url": "https://www.sendgrid.com/en-us/solutions/email-api/dynamic-email-templates"
            },
            {
              "title": "Email Infrastructure",
              "description": "",
              "url": "https://www.sendgrid.com/en-us/solutions/email-api/proven-email-infrastructure"
            },
            {
              "title": "Email Automation",
              "description": "",
              "url": "https://www.sendgrid.com/en-us/solutions/email-marketing/automation"
            },
            {
              "title": "Email Testing",
              "description": "",
              "url": "https://www.sendgrid.com/en-us/solutions/email-marketing/email-testing"
            },
            {
              "title": "Email Design",
              "description": "",
              "url": "https://www.sendgrid.com/en-us/solutions/email-marketing/email-design"
            },
            {
              "title": "Email Templates",
              "description": "",
              "url": "https://www.sendgrid.com/en-us/solutions/email-marketing/email-templates"
            },
            {
              "title": "Email Statistics",
              "description": "",
              "url": "https://www.sendgrid.com/en-us/solutions/email-marketing/email-statistics"
            },
            {
              "title": "Set-Up Assistance",
              "description": "",
              "url": "https://www.twilio.com/en-us/professional-services"
            },
            {
              "title": "Developers",
              "description": "",
              "url": "https://www.sendgrid.com/en-us/solutions/email-api"
            },
            {
              "title": "Startups",
              "description": "",
              "url": "https://www.twilio.com/en-us/solutions/startups-resources"
            },
            {
              "title": "High-Volume Senders",
              "description": "",
              "url": "https://www.sendgrid.com/en-us/contact"
            },
            {
              "title": "Marketers",
              "description": "",
              "url": "https://www.sendgrid.com/en-us/solutions/email-marketing"
            },
            {
              "title": "Enterprises",
              "description": "",
              "url": "https://www.sendgrid.com/en-us/solutions/enterprise"
            },
            {
              "title": "Ecommerce",
              "description": "",
              "url": "https://www.twilio.com/en-us/solutions/ecommerce"
            },
            {
              "title": "Customer Stories",
              "description": "",
              "url": "https://customers.twilio.com/en-us/sendgrid?page=1&products=email%2Cmarketing-campaigns"
            },
            {
              "title": "Email Marketing Guide",
              "description": "",
              "url": "https://www.twilio.com/en-us/resource-center/email-marketing-guide"
            },
            {
              "title": "FAQ",
              "description": "",
              "url": "https://www.sendgrid.com/en-us/resource/faq"
            },
            {
              "title": "Status",
              "description": "",
              "url": "https://status.sendgrid.com/"
            },
            {
              "title": "Partners",
              "description": "",
              "url": "https://www.sendgrid.com/en-us/partners"
            },
            {
              "title": "Knowledge Center",
              "description": "",
              "url": "https://docs.sendgrid.com/"
            },
            {
              "title": "Privacy and Security",
              "description": "",
              "url": "https://www.sendgrid.com/en-us/policies/security"
            },
            {
              "title": "Inbound Parse Webhook",
              "description": "",
              "url": "https://docs.sendgrid.com/for-developers/parsing-email/setting-up-the-inbound-parse-webhook"
            },
            {
              "title": "URL",
              "description": "",
              "url": "https://docs.sendgrid.com/for-developers/sending-email/curl-examples"
            },
            {
              "title": "Node",
              "description": "",
              "url": "https://github.com/sendgrid/sendgrid-nodejs/"
            },
            {
              "title": "Ruby",
              "description": "",
              "url": "https://github.com/sendgrid/sendgrid-ruby/"
            },
            {
              "title": "PHP",
              "description": "",
              "url": "https://github.com/sendgrid/sendgrid-php/"
            },
            {
              "title": "Go",
              "description": "",
              "url": "https://github.com/sendgrid/sendgrid-go/"
            },
            {
              "title": "Python",
              "description": "",
              "url": "https://github.com/sendgrid/sendgrid-python/"
            },
            {
              "title": "Java",
              "description": "",
              "url": "https://github.com/sendgrid/sendgrid-java/"
            },
            {
              "title": "Email Automation",
              "description": "",
              "url": "https://www.sendgrid.com/"
            }
          ]
        }
      ]
    }
  ]
}